celerite/celerite_version.py
celerite/celerite.py
celerite/terms.py
celerite/plot_setup.py
celerite/modeling.py
celerite/timer.py
celerite/solver.cpython-312-x86_64-linux-gnu.so
celerite/solver.cpp
celerite/build.py
celerite/__init__.py
celerite-0.4.3.dist-info/AUTHORS.rst
celerite-0.4.3.dist-info/zip-safe
celerite-0.4.3.dist-info/LICENSE
celerite-0.4.3.dist-info/WHEEL
celerite-0.4.3.dist-info/top_level.txt
celerite-0.4.3.dist-info/RECORD
celerite-0.4.3.dist-info/METADATA
